{"inkVersion":20,"root":[["^n Давай, Денис, делай записи.","\n","^c Я вас слушаю!","\n","^n В 1831 году Майкл Фарадей экспериментально обнаружил возникновение электрического тока в замкнутом проводящем контуре...","\n","^n Ой, как непросто теперь говорить-то...","\n","^n Т-а-а-к... возникновение тока в контуре при любом изменении магнитного потока, пронизывающего данный контур.","\n","^n Классические опыты Фарадея ярко демонстрируют явление электромагнитной индукции.","\n","^c Т-а-а-к...","\n",["done",{"#f":5,"#n":"g-0"}],null],"done",{"#f":1}],"listDefs":{}}